QuickMD/__init__.py
QuickMD/cli.py
QuickMD-0.1.3.dist-info/METADATA
QuickMD-0.1.3.dist-info/WHEEL
QuickMD-0.1.3.dist-info/entry_points.txt
QuickMD-0.1.3.dist-info/top_level.txt
QuickMD-0.1.3.dist-info/RECORD
