Metadata-Version: 2.1
Name: QuickMD
Version: 0.1.3
Summary: Command Line Tool that quickly generates markdown files from your docstrings
Home-page: https://github.com/JaredTPonting/QuickMD
Author: Jared T Ponting
Author-email: jaredtponting@gmail.com
Classifier: Programming Language :: Python :: 3
Requires-Python: >3.6
